LICENSE
MANIFEST.in
README.md
requirements.txt
setup.py
flask_bigtempo/__init__.py
flask_bigtempo/utils.py
flask_bigtempo.egg-info/PKG-INFO
flask_bigtempo.egg-info/SOURCES.txt
flask_bigtempo.egg-info/dependency_links.txt
flask_bigtempo.egg-info/not-zip-safe
flask_bigtempo.egg-info/requires.txt
flask_bigtempo.egg-info/top_level.txt
flask_bigtempo/bigtempo/__init__.py
flask_bigtempo/bigtempo/blueprint.py
flask_bigtempo/bigtempo/clients.py
flask_bigtempo/bigtempo/core.py
flask_bigtempo/bigtempo/datastores.py
flask_bigtempo/bigtempo/defaults.py
flask_bigtempo/store/__init__.py
flask_bigtempo/store/blueprint.py
flask_bigtempo/store/clients.py
flask_bigtempo/store/core.py
flask_bigtempo/store/datasources.py
flask_bigtempo/store/defaults.py
flask_bigtempo/store/storages.py
scripts/bigtempo_api
scripts/store_api